rgd_imagery_client/__init__.py
rgd_imagery_client/_version.py
rgd_imagery_client/plugin.py
rgd_imagery_client/types.py
rgd_imagery_client-0.3.11.dist-info/METADATA
rgd_imagery_client-0.3.11.dist-info/WHEEL
rgd_imagery_client-0.3.11.dist-info/entry_points.txt
rgd_imagery_client-0.3.11.dist-info/top_level.txt
rgd_imagery_client-0.3.11.dist-info/RECORD
